{
"type": "FeatureCollection",
"crs": { "type": "name", "properties": { "name": "urn:ogc:def:crs:EPSG::26911" } },
"features": [
{ "type": "Feature", "properties": { }, "geometry": { "type": "Point", "coordinates": [ 546653.6091, 3742710.009 ] } },
{ "type": "Feature", "properties": { }, "geometry": { "type": "Point", "coordinates": [ 546670.995, 3742687.785 ] } },
{ "type": "Feature", "properties": { }, "geometry": { "type": "Point", "coordinates": [ 546664.0583, 3742693.957 ] } },
{ "type": "Feature", "properties": { }, "geometry": { "type": "Point", "coordinates": [ 546685.4416, 3742612.334 ] } },
{ "type": "Feature", "properties": { }, "geometry": { "type": "Point", "coordinates": [ 546680.962199999951, 3742622.313 ] } },
{ "type": "Feature", "properties": { }, "geometry": { "type": "Point", "coordinates": [ 546680.088499999954, 3742629.807 ] } },
{ "type": "Feature", "properties": { }, "geometry": { "type": "Point", "coordinates": [ 546685.428199999966, 3742632.467 ] } },
{ "type": "Feature", "properties": { }, "geometry": { "type": "Point", "coordinates": [ 546691.3003, 3742629.788 ] } },
{ "type": "Feature", "properties": { }, "geometry": { "type": "Point", "coordinates": [ 546695.1003, 3742622.933 ] } },
{ "type": "Feature", "properties": { }, "geometry": { "type": "Point", "coordinates": [ 546683.3041, 3742638.913 ] } },
{ "type": "Feature", "properties": { }, "geometry": { "type": "Point", "coordinates": [ 546670.424, 3742662.594 ] } },
{ "type": "Feature", "properties": { }, "geometry": { "type": "Point", "coordinates": [ 546655.9348, 3742664.771 ] } },
{ "type": "Feature", "properties": { }, "geometry": { "type": "Point", "coordinates": [ 546696.8161, 3742614.40199999977 ] } },
{ "type": "Feature", "properties": { }, "geometry": { "type": "Point", "coordinates": [ 546700.705199999968, 3742597.416 ] } },
{ "type": "Feature", "properties": { }, "geometry": { "type": "Point", "coordinates": [ 546636.100699999952, 3742679.574 ] } },
{ "type": "Feature", "properties": { }, "geometry": { "type": "Point", "coordinates": [ 546638.898, 3742677.08 ] } },
{ "type": "Feature", "properties": { }, "geometry": { "type": "Point", "coordinates": [ 546649.625699999975, 3742685.833 ] } },
{ "type": "Feature", "properties": { }, "geometry": { "type": "Point", "coordinates": [ 546646.0757, 3742662.18 ] } },
{ "type": "Feature", "properties": { }, "geometry": { "type": "Point", "coordinates": [ 546651.37, 3742655.488 ] } },
{ "type": "Feature", "properties": { }, "geometry": { "type": "Point", "coordinates": [ 546658.684, 3742645.858 ] } },
{ "type": "Feature", "properties": { }, "geometry": { "type": "Point", "coordinates": [ 546668.105699999956, 3742635.061 ] } },
{ "type": "Feature", "properties": { }, "geometry": { "type": "Point", "coordinates": [ 546648.9431, 3742675.52699999977 ] } },
{ "type": "Feature", "properties": { }, "geometry": { "type": "Point", "coordinates": [ 546622.3556, 3742699.834 ] } },
{ "type": "Feature", "properties": { }, "geometry": { "type": "Point", "coordinates": [ 546620.462799999979, 3742721.30899999989 ] } },
{ "type": "Feature", "properties": { }, "geometry": { "type": "Point", "coordinates": [ 546635.7609, 3742709.67199999979 ] } },
{ "type": "Feature", "properties": { }, "geometry": { "type": "Point", "coordinates": [ 546699.554499999969, 3742599.78899999987 ] } },
{ "type": "Feature", "properties": { }, "geometry": { "type": "Point", "coordinates": [ 546701.6027, 3742607.97 ] } },
{ "type": "Feature", "properties": { }, "geometry": { "type": "Point", "coordinates": [ 546656.9472, 3742648.804 ] } },
{ "type": "Feature", "properties": { }, "geometry": { "type": "Point", "coordinates": [ 546642.176, 3742665.304 ] } },
{ "type": "Feature", "properties": { }, "geometry": { "type": "Point", "coordinates": [ 546658.9795, 3742658.35699999984 ] } },
{ "type": "Feature", "properties": { }, "geometry": { "type": "Point", "coordinates": [ 546633.4318, 3742707.915 ] } },
{ "type": "Feature", "properties": { }, "geometry": { "type": "Point", "coordinates": [ 546646.3283, 3742684.781 ] } },
{ "type": "Feature", "properties": { }, "geometry": { "type": "Point", "coordinates": [ 546649.1661, 3742688.992 ] } },
{ "type": "Feature", "properties": { }, "geometry": { "type": "Point", "coordinates": [ 546649.898399999947, 3742682.126 ] } },
{ "type": "Feature", "properties": { }, "geometry": { "type": "Point", "coordinates": [ 546645.4129, 3742682.217 ] } },
{ "type": "Feature", "properties": { }, "geometry": { "type": "Point", "coordinates": [ 546645.779, 3742688.168 ] } },
{ "type": "Feature", "properties": { }, "geometry": { "type": "Point", "coordinates": [ 546662.3482, 3742638.46 ] } }
]
}
